mapcalc/__init__.py
mapcalc/main.py
mapcalc-0.2.2.dist-info/LICENSE
mapcalc-0.2.2.dist-info/METADATA
mapcalc-0.2.2.dist-info/WHEEL
mapcalc-0.2.2.dist-info/top_level.txt
mapcalc-0.2.2.dist-info/RECORD
