Metadata-Version: 2.1
Name: mapcalc
Version: 0.2.2
Summary: Calculates the mAP value in object detection tasks
Home-page: https://github.com/LeMuecke/mapcalc
Author: Simon Klimaschka
Author-email: simon.klimaschka@gmail.com
License: apache-2.0
Download-URL: https://github.com/LeMuecke/mapcalc/archive/v_0.2.2-beta.tar.gz
Keywords: object detection,map,mean average precision
Platform: UNKNOWN
Classifier: Development Status :: 4 - Beta
Classifier: Intended Audience :: Developers
Classifier: Topic :: Software Development :: Build Tools
Classifier: License :: OSI Approved :: Apache Software License
Classifier: Programming Language :: Python :: 3
Classifier: Programming Language :: Python :: 3.4
Classifier: Programming Language :: Python :: 3.5
Classifier: Programming Language :: Python :: 3.6
Classifier: Programming Language :: Python :: 3.7
Classifier: Programming Language :: Python :: 3.8
Classifier: Programming Language :: Python :: 3.9
License-File: LICENSE
Requires-Dist: numpy
